cpapp/__init__.py
cpapp/main.py
cpapp-0.1.0.dist-info/METADATA
cpapp-0.1.0.dist-info/WHEEL
cpapp-0.1.0.dist-info/entry_points.txt
cpapp-0.1.0.dist-info/top_level.txt
cpapp-0.1.0.dist-info/RECORD
