Metadata-Version: 2.1
Name: cpapp
Version: 0.1.0
Summary: A command-line tool to copy file contents based on extension.
Home-page: https://github.com/HakimiX/cpapp
Author: Your Name
Author-email: mustafa.hakimi@outlook.dk
Classifier: Programming Language :: Python :: 3
Classifier: License :: OSI Approved :: MIT License
Classifier: Operating System :: OS Independent
Requires-Python: >=3.6
